[
    {
        "img_large": "http://localhost:5173/img/dishes/burgers/dish-burger.webp",
        "alt_large": "A chicken dish.",
        "img_small_first": "http://localhost:5173/img/dishes/burgers/dish-burger.webp",
        "alt_small_first": "#",
        "img_small_second": "http://localhost:5173/img/dishes/burgers/dish-burger.webp",
        "alt_small_second": "#",
        "img_small_third": "http://localhost:5173/img/dishes/burgers/dish-burger.webp",
        "alt_small_third": "#",
        "name": "fgsgtshzszhsux",
        "description": "Joker burger. Made with angus beef and a lots of hot pepper. Be careful with this beast.",
        "price": "12.99",
        "reviews": "32",
        "rating": "5",
        "sold": "0",
        "type": "Burger"
    },
    {
        "img_large": "http://localhost:5173/img/dishes/burgers/dish-burger.webp",
        "alt_large": "A chicken dish.",
        "img_small_first": "http://localhost:5173/img/dishes/burgers/dish-burger.webp",
        "alt_small_first": "#",
        "img_small_second": "http://localhost:5173/img/dishes/burgers/dish-burger.webp",
        "alt_small_second": "#",
        "img_small_third": "http://localhost:5173/img/dishes/burgers/dish-burger.webp",
        "alt_small_third": "#",
        "name": "Partisan Burger",
        "description": "This is a partisan burger.",
        "price": "21.99",
        "reviews": "56",
        "rating": "5",
        "sold": "0",
        "type": "Burger"
    },
    {
        "img_large": "http://localhost:5173/img/dishes/burgers/dish-burger.webp",
        "alt_large": "A chicken dish.",
        "img_small_first": "http://localhost:5173/img/dishes/burgers/dish-burger.webp",
        "alt_small_first": "#",
        "img_small_second": "http://localhost:5173/img/dishes/burgers/dish-burger.webp",
        "alt_small_second": "#",
        "img_small_third": "http://localhost:5173/img/dishes/burgers/dish-burger.webp",
        "alt_small_third": "#",
        "name": "Ultra Burger",
        "description": "This is a test description which is subject to change later.",
        "price": "15.99",
        "reviews": "85",
        "rating": "5",
        "sold": "0",
        "type": "Burger"
    },
    {
        "img_large": "http://localhost:5173/img/dishes/burgers/dish-burger.webp",
        "alt_large": "A chicken dish.",
        "img_small_first": "http://localhost:5173/img/dishes/burgers/dish-burger.webp",
        "alt_small_first": "#",
        "img_small_second": "http://localhost:5173/img/dishes/burgers/dish-burger.webp",
        "alt_small_second": "#",
        "img_small_third": "http://localhost:5173/img/dishes/burgers/dish-burger.webp",
        "alt_small_third": "#",
        "name": "Killer Burger",
        "description": "This is a test description which is subject to change later.",
        "price": "29.99",
        "reviews": "54",
        "rating": "5",
        "sold": "0",
        "type": "Burger"
    },
    {
        "img_large": "http://localhost:5173/img/dishes/burgers/dish-burger.webp",
        "alt_large": "A chicken dish.",
        "img_small_first": "http://localhost:5173/img/dishes/burgers/dish-burger.webp",
        "alt_small_first": "#",
        "img_small_second": "http://localhost:5173/img/dishes/burgers/dish-burger.webp",
        "alt_small_second": "#",
        "img_small_third": "http://localhost:5173/img/dishes/burgers/dish-burger.webp",
        "alt_small_third": "#",
        "name": "John Burger",
        "description": "This is a test description which is subject to change later.",
        "price": "8.99",
        "reviews": "81",
        "rating": "5",
        "sold": "0",
        "type": "Burger"
    }
]